setup.cfg
setup.py
tinyfpgab/__init__.py
tinyfpgab/__main__.py
tinyfpgab.egg-info/PKG-INFO
tinyfpgab.egg-info/SOURCES.txt
tinyfpgab.egg-info/dependency_links.txt
tinyfpgab.egg-info/entry_points.txt
tinyfpgab.egg-info/requires.txt
tinyfpgab.egg-info/top_level.txt