Metadata-Version: 1.0
Name: tinyfpgab
Version: 1.1.0
Summary: Programmer for the TinyFPGA B2 boards (http://tinyfpga.com)
Home-page: https://github.com/tinyfpga/TinyFPGA-B-Series/tree/master/programmer
Author: Luke Valenty
Author-email: lvalenty@gmail.com
License: UNKNOWN
Keywords: fpga,tinyfpga,programmer
Platform: UNKNOWN
